portfinder/__init__.py
portfinder/cli.py
portfinder/dto.py
portfinder/scanner.py
portfinder/utils/__init__.py
portfinder/utils/file.py
portfinder/utils/request.py
portfinder-0.1.8.dist-info/LICENSE
portfinder-0.1.8.dist-info/METADATA
portfinder-0.1.8.dist-info/WHEEL
portfinder-0.1.8.dist-info/entry_points.txt
portfinder-0.1.8.dist-info/RECORD
